{"ProjectBreakpoints":"{\"Value\":{\"Main.xaml\":[{\"ConditionalExpression\":null,\"ActionExpression\":null,\"ExpectedHitCounter\":null,\"ShouldContinueAfterAction\":false,\"BreakpointType\":1,\"LocationIdentifier\":\"Check Element 'Log In bebee.com'\",\"IsEnabled\":true,\"Annotation\":null,\"Id\":\"3b90aff0-360d-4013-8791-ff3bc551f821\",\"ActivityIdRef\":\"NCheckElement_6\",\"ActivityId\":\"1.215\",\"ActivityName\":\"Check Element 'Log In bebee.com'\",\"IsTransient\":false},{\"ConditionalExpression\":null,\"ActionExpression\":null,\"ExpectedHitCounter\":null,\"ShouldContinueAfterAction\":false,\"BreakpointType\":1,\"LocationIdentifier\":\"Try\",\"IsEnabled\":true,\"Annotation\":null,\"Id\":\"0a2485cf-7030-4c94-a35b-b9be007071c9\",\"ActivityIdRef\":\"Sequence_47\",\"ActivityId\":\"1.105\",\"ActivityName\":\"Try\",\"IsTransient\":false}]},\"CodeBreakpoints\":{}}","Compiler":"2","ProjectWatches":"{\"Value\":[{\"Id\":\"0cddded6-c1b1-4467-91da-27e3d1dfbfec\",\"Expression\":\"is_loginBtn\",\"Type\":0},{\"Id\":\"19b8686d-96b8-4d9c-83e4-23182f2b449d\",\"Expression\":\"CurrentAddress\",\"Type\":0},{\"Id\":\"4c43d67f-a29b-4539-b363-c528344d33d8\",\"Expression\":\"exists_login\",\"Type\":0}]}","OpenedDocuments":"[{\"DocumentPath\":\"Main.xaml\",\"FactoryId\":\"{ACB8E7BA-F093-44C1-9B50-33ECA51AAE16}\"}]","ProjectActivitiesViewState":"{\"Main.xaml\":[{\"ActivityIdRef\":\"LogMessage_1\",\"IsAdvancedOptionsExpanded\":false,\"Widgets\":{}},{\"ActivityIdRef\":\"LogMessage_2\",\"IsAdvancedOptionsExpanded\":false,\"Widgets\":{}},{\"ActivityIdRef\":\"LogMessage_3\",\"IsAdvancedOptionsExpanded\":false,\"Widgets\":{}},{\"ActivityIdRef\":\"Switch`1_1\",\"IsAdvancedOptionsExpanded\":false,\"Widgets\":{\"Default\":{\"ShowExpanded\":true}}},{\"ActivityIdRef\":\"ForEachRow_1\",\"IsAdvancedOptionsExpanded\":false,\"Categories\":{\"\":true},\"Widgets\":{\"Body\":{\"ShowExpanded\":true}}},{\"ActivityIdRef\":\"LogMessage_4\",\"IsAdvancedOptionsExpanded\":false,\"Widgets\":{}},{\"ActivityIdRef\":\"If_1\",\"IsAdvancedOptionsExpanded\":false,\"Widgets\":{\"Then\":{\"ShowExpanded\":true},\"Else\":{\"ShowExpanded\":true}}},{\"ActivityIdRef\":\"TryCatch_1\",\"IsAdvancedOptionsExpanded\":false,\"Widgets\":{\"Try\":{\"ShowExpanded\":true},\"Finally\":{\"ShowExpanded\":true}}},{\"ActivityIdRef\":\"LogMessage_5\",\"IsAdvancedOptionsExpanded\":false,\"Widgets\":{}},{\"ActivityIdRef\":\"TryCatch_2\",\"IsAdvancedOptionsExpanded\":false,\"Widgets\":{\"Try\":{\"ShowExpanded\":true},\"Finally\":{\"ShowExpanded\":true}}},{\"ActivityIdRef\":\"LogMessage_6\",\"IsAdvancedOptionsExpanded\":false,\"Widgets\":{}},{\"ActivityIdRef\":\"LogMessage_7\",\"IsAdvancedOptionsExpanded\":false,\"Widgets\":{}},{\"ActivityIdRef\":\"If_2\",\"IsAdvancedOptionsExpanded\":false,\"Widgets\":{\"Then\":{\"ShowExpanded\":true},\"Else\":{\"ShowExpanded\":true}}},{\"ActivityIdRef\":\"TryCatch_3\",\"IsAdvancedOptionsExpanded\":false,\"Widgets\":{\"Try\":{\"ShowExpanded\":true},\"Finally\":{\"ShowExpanded\":true}}},{\"ActivityIdRef\":\"LogMessage_8\",\"IsAdvancedOptionsExpanded\":false,\"Widgets\":{}},{\"ActivityIdRef\":\"TryCatch_4\",\"IsAdvancedOptionsExpanded\":false,\"Widgets\":{\"Try\":{\"ShowExpanded\":true},\"Finally\":{\"ShowExpanded\":true}}},{\"ActivityIdRef\":\"LogMessage_9\",\"IsAdvancedOptionsExpanded\":false,\"Widgets\":{}},{\"ActivityIdRef\":\"LogMessage_10\",\"IsAdvancedOptionsExpanded\":false,\"Widgets\":{}},{\"ActivityIdRef\":\"TryCatch_5\",\"IsAdvancedOptionsExpanded\":false,\"Widgets\":{\"Try\":{\"ShowExpanded\":true},\"Finally\":{\"ShowExpanded\":true}}},{\"ActivityIdRef\":\"LogMessage_11\",\"IsAdvancedOptionsExpanded\":false,\"Widgets\":{}},{\"ActivityIdRef\":\"LogMessage_12\",\"IsAdvancedOptionsExpanded\":false,\"Widgets\":{}},{\"ActivityIdRef\":\"TryCatch_6\",\"IsAdvancedOptionsExpanded\":false,\"Widgets\":{\"Try\":{\"ShowExpanded\":true},\"Finally\":{\"ShowExpanded\":true}}},{\"ActivityIdRef\":\"LogMessage_13\",\"IsAdvancedOptionsExpanded\":false,\"Widgets\":{}},{\"ActivityIdRef\":\"TryCatch_7\",\"IsAdvancedOptionsExpanded\":false,\"Widgets\":{\"Try\":{\"ShowExpanded\":true},\"Finally\":{\"ShowExpanded\":true}}},{\"ActivityIdRef\":\"If_3\",\"IsAdvancedOptionsExpanded\":false,\"Widgets\":{\"Then\":{\"ShowExpanded\":true},\"Else\":{\"ShowExpanded\":true}}},{\"ActivityIdRef\":\"LogMessage_14\",\"IsAdvancedOptionsExpanded\":false,\"Widgets\":{}},{\"ActivityIdRef\":\"TryCatch_8\",\"IsAdvancedOptionsExpanded\":false,\"Widgets\":{\"Try\":{\"ShowExpanded\":true},\"Finally\":{\"ShowExpanded\":true}}},{\"ActivityIdRef\":\"LogMessage_15\",\"IsAdvancedOptionsExpanded\":false,\"Widgets\":{}},{\"ActivityIdRef\":\"LogMessage_18\",\"IsAdvancedOptionsExpanded\":false,\"Widgets\":{}},{\"ActivityIdRef\":\"TryCatch_9\",\"IsAdvancedOptionsExpanded\":false,\"Widgets\":{\"Try\":{\"ShowExpanded\":true},\"Finally\":{\"ShowExpanded\":true}}},{\"ActivityIdRef\":\"LogMessage_16\",\"IsAdvancedOptionsExpanded\":false,\"Widgets\":{}},{\"ActivityIdRef\":\"LogMessage_19\",\"IsAdvancedOptionsExpanded\":false,\"Widgets\":{}},{\"ActivityIdRef\":\"LogMessage_17\",\"IsAdvancedOptionsExpanded\":false,\"Widgets\":{}},{\"ActivityIdRef\":\"LogMessage_20\",\"IsAdvancedOptionsExpanded\":false,\"Widgets\":{}},{\"ActivityIdRef\":\"LogMessage_21\",\"IsAdvancedOptionsExpanded\":false,\"Widgets\":{}},{\"ActivityIdRef\":\"TryCatch_10\",\"IsAdvancedOptionsExpanded\":false,\"Widgets\":{\"Try\":{\"ShowExpanded\":true},\"Finally\":{\"ShowExpanded\":true}}},{\"ActivityIdRef\":\"If_4\",\"IsAdvancedOptionsExpanded\":false,\"Widgets\":{\"Then\":{\"ShowExpanded\":true},\"Else\":{\"ShowExpanded\":true}}},{\"ActivityIdRef\":\"LogMessage_22\",\"IsAdvancedOptionsExpanded\":false,\"Widgets\":{}},{\"ActivityIdRef\":\"TryCatch_11\",\"IsAdvancedOptionsExpanded\":false,\"Widgets\":{\"Try\":{\"ShowExpanded\":true},\"Finally\":{\"ShowExpanded\":true}}},{\"ActivityIdRef\":\"TryCatch_12\",\"IsAdvancedOptionsExpanded\":false,\"Widgets\":{\"Try\":{\"ShowExpanded\":true},\"Finally\":{\"ShowExpanded\":true}}},{\"ActivityIdRef\":\"LogMessage_26\",\"IsAdvancedOptionsExpanded\":false,\"Widgets\":{}},{\"ActivityIdRef\":\"LogMessage_23\",\"IsAdvancedOptionsExpanded\":false,\"Widgets\":{}},{\"ActivityIdRef\":\"LogMessage_24\",\"IsAdvancedOptionsExpanded\":false,\"Widgets\":{}},{\"ActivityIdRef\":\"LogMessage_25\",\"IsAdvancedOptionsExpanded\":false,\"Widgets\":{}},{\"ActivityIdRef\":\"LogMessage_27\",\"IsAdvancedOptionsExpanded\":false,\"Widgets\":{}}]}"}